dagsesh/__init__.py
dagsesh/lazy.py
dagsesh/logging_config.py
dagsesh/plugin.py
dagsesh/py.typed
dagsesh-0.1.1.dist-info/licenses/LICENSE.md
dagsesh-0.1.1.dist-info/METADATA
dagsesh-0.1.1.dist-info/WHEEL
dagsesh-0.1.1.dist-info/entry_points.txt
dagsesh-0.1.1.dist-info/top_level.txt
dagsesh-0.1.1.dist-info/RECORD
