Metadata-Version: 2.4
Name: dagsesh
Version: 0.1.1
Summary: Flowz workflow management
Author-email: Lou Markovski <lou.markovski@gmail.com>
License-Expression: MIT
Project-URL: Documentation, https://loum.github.io/dagsesh/
Project-URL: Repository, https://github.com/loum/dagsesh
Project-URL: Issues, https://github.com/loum/dagsesh/issues
Classifier: Development Status :: 5 - Production/Stable
Classifier: Environment :: Console
Classifier: Environment :: MacOS X
Classifier: Intended Audience :: Developers
Classifier: Topic :: Software Development :: Build Tools
Classifier: Natural Language :: English
Classifier: Operating System :: POSIX :: Linux
Classifier: Operating System :: MacOS :: MacOS X
Classifier: Programming Language :: Python :: 3
Requires-Python: <3.13,>=3.9
License-File: LICENSE.md
Requires-Dist: Flask-Limiter<3.13
Requires-Dist: pytest
Requires-Dist: structlog
Provides-Extra: dev
Requires-Dist: apache-airflow==2.10.*; extra == "dev"
Requires-Dist: black; extra == "dev"
Requires-Dist: build; extra == "dev"
Requires-Dist: deptry; extra == "dev"
Requires-Dist: mdformat; extra == "dev"
Requires-Dist: mdformat-mkdocs; extra == "dev"
Requires-Dist: mkdocs-material; extra == "dev"
Requires-Dist: mkdocstrings-python; extra == "dev"
Requires-Dist: mypy; extra == "dev"
Requires-Dist: pytest; extra == "dev"
Requires-Dist: pytest-cov; extra == "dev"
Requires-Dist: pytest-sugar; extra == "dev"
Requires-Dist: ruff; extra == "dev"
Requires-Dist: sqlalchemy2-stubs; extra == "dev"
Requires-Dist: twine; extra == "dev"
Requires-Dist: types-pytz; extra == "dev"
Dynamic: license-file
